gym_multigrid/__init__.py
gym_multigrid/core/agent.py
gym_multigrid/core/constants.py
gym_multigrid/core/grid.py
gym_multigrid/core/object.py
gym_multigrid/core/world.py
gym_multigrid/envs/__init__.py
gym_multigrid/envs/collect_game.py
gym_multigrid/envs/ctf.py
gym_multigrid/envs/maze.py
gym_multigrid/multigrid.py
gym_multigrid/policy/__init__.py
gym_multigrid/policy/base.py
gym_multigrid/policy/ctf/__init__.py
gym_multigrid/policy/ctf/heuristic.py
gym_multigrid/policy/ctf/utils.py
gym_multigrid/typing.py
gym_multigrid/utils/__init__.py
gym_multigrid/utils/map.py
gym_multigrid/utils/misc.py
gym_multigrid/utils/rendering.py
gym_multigrid/utils/window.py
gym_multigrid/wrappers/__init__.py
gym_multigrid/wrappers/toroid.py
gym_multigrid-1.0.0.dist-info/METADATA
gym_multigrid-1.0.0.dist-info/WHEEL
gym_multigrid-1.0.0.dist-info/RECORD
