Metadata-Version: 2.1
Name: gym-multigrid
Version: 1.0.0
Summary: Muti-agent gymnasium gridworld environments
License: Apache-2.0
Author: Mikihisa Yuasa
Author-email: myuasa2@illinois.edu
Requires-Python: >=3.10
Classifier: License :: OSI Approved :: Apache Software License
Classifier: Programming Language :: Python :: 3
Classifier: Programming Language :: Python :: 3.10
Classifier: Programming Language :: Python :: 3.11
Classifier: Programming Language :: Python :: 3.12
Requires-Dist: gymnasium (>=0.28)
Requires-Dist: imageio (>=2.28.1)
Requires-Dist: matplotlib (>=3.7.1)
Requires-Dist: numpy (>=1.24.3)
